[
  {
    "id": "civil-law",
    "name": "Civil Law",
    "codals": [
      {
        "title": "Civil Code of the Philippines (RA 386)",
        "url": "https://lawphil.net/statutes/repacts/ra1949/ra_386_1949.html",
        "articles": 2270,
        "status": "verified"
      },
      {
        "title": "Family Code of the Philippines (EO 209)",
        "url": "https://lawphil.net/executive/execord/eo1987/eo_209_1987.html",
        "articles": 256,
        "status": "verified"
      },
      {
        "title": "Property Registration Decree (PD 1529)",
        "url": "https://lawphil.net/statutes/presdecs/pd1978/pd_1529_1978.html",
        "sections": 120,
        "status": "verified"
      }
    ],
    "textbooks": ["Arturo M. Tolentino (Vols. I-V)", "Eduardo L. Paras (Vols. I-V)", "Elmer T. Rabuya (Reviewer)"]
  },
  {
    "id": "criminal-law",
    "name": "Criminal Law",
    "codals": [
      {
        "title": "Revised Penal Code (Act 3815)",
        "url": "https://lawphil.net/statutes/acts/act1930/act_3815_1930.html",
        "articles": 367,
        "status": "verified"
      },
      {
        "title": "Dangerous Drugs Act of 2002 (RA 9165)",
        "url": "https://lawphil.net/statutes/repacts/ra2002/ra_9165_2002.html",
        "sections": 102,
        "status": "verified"
      }
    ],
    "textbooks": ["Luis B. Reyes (Books 1 & 2)", "Justice Florenz D. Regalado (Conspectus)", "Campanilla/Ortega (Reviewer)"]
  },
  {
    "id": "political-law",
    "name": "Political Law",
    "codals": [
      {
        "title": "1987 Constitution of the Philippines",
        "url": "https://lawphil.net/consti/cons1987.html",
        "sections": 321,
        "status": "verified"
      },
      {
        "title": "Local Government Code of 1991 (RA 7160)",
        "url": "https://lawphil.net/statutes/repacts/ra1991/ra_7160_1991.html",
        "sections": 536,
        "status": "verified"
      },
      {
        "title": "Administrative Code of 1987 (EO 292)",
        "url": "https://lawphil.net/statutes/repacts/ra1991/ra_7160_1991.html",
        "sections": 100,
        "status": "alternate"
      }
    ],
    "textbooks": ["Joaquin G. Bernas, S.J. (Commentary)", "Isagani A. Cruz (Constitutional)", "Antonio E.B. Nachura (Outline)"]
  },
  {
    "id": "remedial-law",
    "name": "Remedial Law",
    "codals": [
      {
        "title": "1997 Rules of Civil Procedure (A.M. 19-10-20-SC)",
        "url": "https://sc.judiciary.gov.ph/2019-amendments-to-the-1997-rules-of-civil-procedure/",
        "rules": 71,
        "status": "sc-web"
      },
      {
        "title": "Rules on Evidence (A.M. 19-08-15-SC)",
        "url": "https://sc.judiciary.gov.ph/2019-proposed-amendments-to-the-revised-rules-on-evidence/",
        "rules": 7,
        "status": "sc-web"
      },
      {
        "title": "Rules of Criminal Procedure",
        "url": "https://sc.judiciary.gov.ph/rules-of-court/",
        "rules": 120,
        "status": "sc-web"
      }
    ],
    "textbooks": ["Willard B. Riano (Civil/Crim/Evidence Series)", "Florenz D. Regalado (Compendium)", "Ferdinand A Tan"]
  },
  {
    "id": "commercial-law",
    "name": "Commercial Law",
    "codals": [
      {
        "title": "Revised Corporation Code (RA 11232)",
        "url": "https://lawphil.net/statutes/repacts/ra2019/ra_11232_2019.html",
        "sections": 144,
        "status": "verified"
      },
      {
        "title": "Insurance Code (RA 10607)",
        "url": "https://lawphil.net/statutes/repacts/ra2013/ra_10607_2013.html",
        "sections": 389,
        "status": "verified"
      },
      {
        "title": "Negotiable Instruments Law (Act 2031)",
        "url": "https://lawphil.net/statutes/acts/act1911/act_2031_1911.html",
        "sections": 195,
        "status": "verified"
      }
    ],
    "textbooks": ["Sundiang & Aquino (Reviewer)", "Nilo T. Divina (Divina on Comm)", "Cesar L. Villanueva"]
  },
  {
    "id": "labor-law",
    "name": "Labor Law",
    "codals": [
      {
        "title": "Labor Code of the Philippines (PD 442)",
        "url": "https://lawphil.net/statutes/presdecs/pd1974/pd_442_1974.html",
        "articles": 302,
        "status": "verified"
      }
    ],
    "textbooks": ["Cesario A. Azucena Jr. (Vols. I & II)", "Joselito Guianan Chan (Reviewer)", "Atty. Duano"]
  },
  {
    "id": "taxation",
    "name": "Taxation",
    "codals": [
      {
        "title": "National Internal Revenue Code (NIRC / RA 8424)",
        "url": "https://lawphil.net/statutes/repacts/ra1997/ra_8424_1997.html",
        "sections": 282,
        "status": "verified"
      },
      {
        "title": "Tariff and Customs Code of the Philippines (RA 10863)",
        "url": "https://lawphil.net/statutes/repacts/ra2016/ra_10863_2016.html",
        "sections": 100,
        "status": "verified"
      }
    ],
    "textbooks": ["Justice Japar B. Dimaampao (Principles & Remedies)", "E.P. Ingles (Tax Made Less Taxing)"]
  },
  {
    "id": "legal-ethics",
    "name": "Legal Ethics",
    "codals": [
      {
        "title": "Code of Professional Responsibility and Accountability (CPRA, A.M. 22-09-01-SC)",
        "url": "https://sc.judiciary.gov.ph/rules-of-court/",
        "canons": 6,
        "sections": 82,
        "status": "sc-web"
      },
      {
        "title": "Lawyer's Oath and Canons of Professional Ethics",
        "url": "https://sc.judiciary.gov.ph/",
        "canons": 7,
        "status": "sc-web"
      }
    ],
    "textbooks": ["Ruben E. Agpalo (Legal & Judicial Ethics)", "Atty. Funa / Pineda"]
  }
]
